Metadata-Version: 2.1
Name: operatii-mate
Version: 1.0.0
Summary: Contine operatii simple matematice
Author: Nicu B.
